fraudcrawler/__init__.py
fraudcrawler/base/__init__.py
fraudcrawler/base/base.py
fraudcrawler/base/client.py
fraudcrawler/base/google-languages.json
fraudcrawler/base/google-locations.json
fraudcrawler/base/orchestrator.py
fraudcrawler/launch_demo_pipeline.py
fraudcrawler/processing/__init__.py
fraudcrawler/processing/processor.py
fraudcrawler/scraping/__init__.py
fraudcrawler/scraping/enrich.py
fraudcrawler/scraping/serp.py
fraudcrawler/scraping/zyte.py
fraudcrawler/settings.py
vianu_fraudcrawler-0.3.2.dist-info/LICENSE
vianu_fraudcrawler-0.3.2.dist-info/METADATA
vianu_fraudcrawler-0.3.2.dist-info/WHEEL
vianu_fraudcrawler-0.3.2.dist-info/entry_points.txt
vianu_fraudcrawler-0.3.2.dist-info/RECORD
